examples/__init__.py
examples/wifindme-example.py
examples/wifindme.py
wifindme/__init__.py
wifindme-0.3.0.dist-info/DESCRIPTION.rst
wifindme-0.3.0.dist-info/METADATA
wifindme-0.3.0.dist-info/RECORD
wifindme-0.3.0.dist-info/WHEEL
wifindme-0.3.0.dist-info/metadata.json
wifindme-0.3.0.dist-info/top_level.txt
